README
setup.py
pgpumpy/__init__.py
pgpumpy/tools.py
pgpumpy.egg-info/PKG-INFO
pgpumpy.egg-info/SOURCES.txt
pgpumpy.egg-info/dependency_links.txt
pgpumpy.egg-info/requires.txt
pgpumpy.egg-info/top_level.txt