Metadata-Version: 1.0
Name: pgpumpy
Version: 1.0.12
Summary: A data pump for PostgreSQL, implemented as a Python module.
Home-page: https://github.com/phenicle/pgpumpy
Author: Phenicle
Author-email: pheniclebeefheart@gmail.com
License: Mozilla Public License 2.0 (MPL 2.0)
Platform: UNKNOWN
